compair/__init__.py
compair-0.1.0.dist-info/LICENSE.txt
compair-0.1.0.dist-info/METADATA
compair-0.1.0.dist-info/WHEEL
compair-0.1.0.dist-info/top_level.txt
compair-0.1.0.dist-info/RECORD
